{
    "results":
    [
        {
            "percentage": "25",
            "title": "Ранг S",
            "description": "Очень длинное описание оно описывает результат прохождения теста. Очень длинное описание оно описывает результат прохождения теста. Очень длинное описание оно описывает результат прохождения теста"
        },

        {
            "percentage": "50",
            "title": "Ранг SS",
            "description": "Очень длинное описание оно описывает результат прохождения теста. Очень длинное описание оно описывает результат прохождения теста. Очень длинное описание оно описывает результат прохождения теста"
        },

        {
            "percentage": "75",
            "title": "Ранг SSS",
            "description": "Очень длинное описание оно описывает результат прохождения теста. Очень длинное описание оно описывает результат прохождения теста. Очень длинное описание оно описывает результат прохождения теста"
        },

        {
            "percentage": "80",
            "title": "Ранг SSR",
            "description": "Очень длинное описание оно описывает результат прохождения теста. Очень длинное описание оно описывает результат прохождения теста. Очень длинное описание оно описывает результат прохождения теста"
        }
    ],

    "questions":
    [
        {
            "order": "0",
            "score-point": "1",
            "question": "Какой то вопрос (правда ложь)",
            "answers": ["правда", "ложь"],
            "correct-answer": "правда"
        },

        {
            "order": "1",
            "score-point": "1",
            "question": "Какой то вопрос (5 вариантов ответов <2-true>)",
            "answers": ["вариант 1", "вариант 2", "вариант 3", "вариант 4", "вариант 5"],
            "correct-answer": "вариант 2"
        },

        {
            "order": "2",
            "score-point": "1",
            "question": "Какой то вопрос (3 вариантов ответов <3-true>)",
            "answers": ["вариант 1", "вариант 2", "вариант 3"],
            "correct-answer": "вариант 3"
        },

        {
            "order": "3",
            "score-point": "1",
            "question": "Какой то вопрос c картинкой (3 вариантов ответов <3-true>)",
            "answers": ["вариант 1", "вариант 2", "вариант 3"],
            "correct-answer": "вариант 3",
            "image": "q-Image"
        },

        {
            "order": "4",
            "score-point": "1",
            "question": "Какой то вопрос c картинкой (5 вариантов ответов <2-true>)",
            "answers": ["вариант 1", "вариант 2", "вариант 3", "вариант 4", "вариант 5"],
            "correct-answer": "вариант 2",
            "image": "q-Image"
        },

        {
            "order": "5",
            "score-point": "1",
            "question": "Какой то вопрос c музыкой (5 вариантов ответов <2-true>)",
            "answers": ["вариант 1", "вариант 2", "вариант 3", "вариант 4", "вариант 5"],
            "correct-answer": "вариант 2",
            "muisc": "q-muisc"
        },

        {
            "order": "6",
            "score-point": "1",
            "question": "Какой то вопрос c музыкой (3 вариантов ответов <3-true>)",
            "answers": ["вариант 1", "вариант 2", "вариант 3"],
            "correct-answer": "вариант 3",
            "muisc": "q-muisc"
        },

        {
            "order": "7",
            "score-point": "1",
            "question": "Какой то вопрос c музыкой и картинкой (5 вариантов ответов <2-true>)",
            "answers": ["вариант 1", "вариант 2", "вариант 3", "вариант 4", "вариант 5"],
            "correct-answer": "вариант 2",
            "image": "q-Image",
            "muisc": "q-muisc"
        },

        {
            "order": "8",
            "score-point": "1",
            "question": "Какой то вопрос c музыкой и картинкой (3 вариантов ответов <3-true>)",
            "answers": ["вариант 1", "вариант 2", "вариант 3"],
            "correct-answer": "вариант 3",
            "image": "q-Image",
            "muisc": "q-muisc"
        }
    ]
}